<?xml version="1.0" encoding="utf-8"?>
<doctrine-mapping xmlns="http://doctrine-project.org/schemas/orm/doctrine-mapping" xmlns:xsi="http://www.w3.org/2001/XMLSchema-instance" xsi:schemaLocation="http://doctrine-project.org/schemas/orm/doctrine-mapping http://doctrine-project.org/schemas/orm/doctrine-mapping.xsd">
  <entity name="AppBundle\Entity\Trackingnumber" table="trackingnumber">
    <indexes>
      <index name="IDX_F7F4EA65CB50B99" columns="idcustomsdoc"/>
    </indexes>
    <id name="idtrackingnumber" type="string" column="idtrackingnumber" length="32">
      <generator strategy="SEQUENCE"/>
      <sequence-generator sequence-name="trackingnumber_idtrackingnumber_seq" allocation-size="1" initial-value="1"/>
    </id>
    <field name="idperson" type="integer" column="idperson" nullable="false">
      <options>
        <option name="unsigned"/>
      </options>
    </field>
    <many-to-one field="idcustomsdoc" target-entity="Customsdocuments" fetch="LAZY">
      <join-columns>
        <join-column name="idcustomsdoc" referenced-column-name="idcustomsdoc"/>
      </join-columns>
    </many-to-one>
  </entity>
</doctrine-mapping>
